tradier/__init__.py
tradier/tradier.py
tradier-0.0.1.dist-info/LICENSE
tradier-0.0.1.dist-info/METADATA
tradier-0.0.1.dist-info/WHEEL
tradier-0.0.1.dist-info/top_level.txt
tradier-0.0.1.dist-info/RECORD
