Metadata-Version: 2.1
Name: tradier
Version: 0.0.1
Summary: python client for connecting with tradier
Home-page: https://github.com/jeffhu1/python-tradier
Author: Jeffrey Hu
Author-email: jeffreyhu555@gmail.com
License: UNKNOWN
Platform: UNKNOWN
Classifier: Programming Language :: Python :: 3
Classifier: License :: OSI Approved :: MIT License
Classifier: Operating System :: OS Independent
Requires-Python: >=3.6
Requires-Dist: requests
